mc/__init__.py
mc/mc_functions.py
mcMqttComms-0.1.2.dist-info/METADATA
mcMqttComms-0.1.2.dist-info/WHEEL
mcMqttComms-0.1.2.dist-info/top_level.txt
mcMqttComms-0.1.2.dist-info/RECORD
